add_agent_skill/__init__.py
add_agent_skill-0.0.1.dist-info/METADATA
add_agent_skill-0.0.1.dist-info/WHEEL
add_agent_skill-0.0.1.dist-info/RECORD
