Metadata-Version: 2.4
Name: add-agent-skill
Version: 0.0.1
Summary: CLI tool for adding Claude Code agent skills from GitHub. Coming soon.
Project-URL: Repository, https://github.com/kasperjunge/agent-resources
License-Expression: MIT
Keywords: agent,ai,claude,claude-code,skill
Requires-Python: >=3.10
